langchain_catchall/__init__.py
langchain_catchall/client.py
langchain_catchall/helpers.py
langchain_catchall/prompts.py
langchain_catchall/tools.py
langchain_catchall-0.1.3.dist-info/licenses/LICENSE
langchain_catchall-0.1.3.dist-info/METADATA
langchain_catchall-0.1.3.dist-info/WHEEL
langchain_catchall-0.1.3.dist-info/top_level.txt
langchain_catchall-0.1.3.dist-info/RECORD
