Metadata-Version: 2.4
Name: langchain-catchall
Version: 0.1.3
Summary: LangChain integration for NewsCatcher CatchAll API
Author-email: NewsCatcher <support@newscatcherapi.com>
License: MIT
Project-URL: Homepage, https://github.com/Newscatcher/langchain-catchall
Project-URL: Documentation, https://docs.newscatcherapi.com/
Keywords: langchain,newscatcher,web search,agent
Classifier: Development Status :: 4 - Beta
Classifier: Intended Audience :: Developers
Classifier: License :: OSI Approved :: MIT License
Classifier: Programming Language :: Python :: 3
Classifier: Programming Language :: Python :: 3.9
Classifier: Programming Language :: Python :: 3.10
Classifier: Programming Language :: Python :: 3.11
Classifier: Topic :: Software Development :: Libraries :: Python Modules
Requires-Python: >=3.9
License-File: LICENSE
Requires-Dist: langchain-core>=0.3.0
Requires-Dist: newscatcher-catchall-sdk>=0.2.0
Requires-Dist: pydantic>=2.0.0
Provides-Extra: test
Requires-Dist: pytest>=7.0.0; extra == "test"
Requires-Dist: pytest-asyncio>=0.21.0; extra == "test"
Requires-Dist: langchain-tests>=0.3.0; extra == "test"
Requires-Dist: langchain-openai>=0.1.0; extra == "test"
Dynamic: license-file
